apesmit/__init__.py
apesmit_python2-0.3.dist-info/DESCRIPTION.rst
apesmit_python2-0.3.dist-info/METADATA
apesmit_python2-0.3.dist-info/RECORD
apesmit_python2-0.3.dist-info/WHEEL
apesmit_python2-0.3.dist-info/metadata.json
apesmit_python2-0.3.dist-info/top_level.txt
