Metadata-Version: 2.0
Name: apesmit-python2
Version: 0.3
Summary: simple Python module to create XML sitemaps
Home-page: http://www.florian-diesch.de/software/apesmit/
Author: Michael Cho
Author-email: michael.cho@mail.com
License: GPLv2
Download-URL: http://www.florian-diesch.de/software/apesmit/
Keywords: xml,sitemap,web,website
Platform: UNKNOWN
Classifier: Development Status :: 3 - Alpha
Classifier: Intended Audience :: Developers
Classifier: License :: OSI Approved :: GNU General Public License (GPL)
Classifier: Natural Language :: English
Classifier: Natural Language :: German
Classifier: Operating System :: OS Independent
Classifier: Programming Language :: Python
Classifier: Topic :: Internet :: WWW/HTTP
Classifier: Topic :: Software Development :: Libraries :: Python Modules
